pymsyh/__init__.py
pymsyh/utils.py
pymsyh/data/msyh.ttf
py_msyh-0.0.0.3.dist-info/LICENSE
py_msyh-0.0.0.3.dist-info/METADATA
py_msyh-0.0.0.3.dist-info/WHEEL
py_msyh-0.0.0.3.dist-info/top_level.txt
py_msyh-0.0.0.3.dist-info/RECORD
